CHANGES.rst
COPYING
MANIFEST.in
README.rst
setup.cfg
setup.py
bin/numinwords
numinwords/__init__.py
numinwords/base.py
numinwords/compat.py
numinwords/currency.py
numinwords/lang_AR.py
numinwords/lang_CZ.py
numinwords/lang_DE.py
numinwords/lang_DK.py
numinwords/lang_EN.py
numinwords/lang_EN_IN.py
numinwords/lang_ES.py
numinwords/lang_ES_CO.py
numinwords/lang_ES_NI.py
numinwords/lang_ES_VE.py
numinwords/lang_EU.py
numinwords/lang_FI.py
numinwords/lang_FR.py
numinwords/lang_FR_BE.py
numinwords/lang_FR_CH.py
numinwords/lang_FR_DZ.py
numinwords/lang_HE.py
numinwords/lang_ID.py
numinwords/lang_IT.py
numinwords/lang_JA.py
numinwords/lang_KN.py
numinwords/lang_KO.py
numinwords/lang_KZ.py
numinwords/lang_LT.py
numinwords/lang_LV.py
numinwords/lang_NL.py
numinwords/lang_NO.py
numinwords/lang_PL.py
numinwords/lang_PT.py
numinwords/lang_PT_BR.py
numinwords/lang_RO.py
numinwords/lang_RU.py
numinwords/lang_SL.py
numinwords/lang_SR.py
numinwords/lang_TE.py
numinwords/lang_TH.py
numinwords/lang_TR.py
numinwords/lang_UK.py
numinwords/lang_VI.py
numinwords/utils.py
numinwords.egg-info/PKG-INFO
numinwords.egg-info/SOURCES.txt
numinwords.egg-info/dependency_links.txt
numinwords.egg-info/requires.txt
numinwords.egg-info/top_level.txt
tests/__init__.py
tests/__init__.pyc
tests/test_ar.py
tests/test_ar.pyc
tests/test_base.py
tests/test_base.pyc
tests/test_cli.py
tests/test_cli.pyc
tests/test_currency.py
tests/test_currency.pyc
tests/test_cz.py
tests/test_cz.pyc
tests/test_de.py
tests/test_de.pyc
tests/test_dk.py
tests/test_dk.pyc
tests/test_en.py
tests/test_en.pyc
tests/test_en_in.py
tests/test_en_in.pyc
tests/test_errors.py
tests/test_errors.pyc
tests/test_es.py
tests/test_es.pyc
tests/test_es_co.py
tests/test_es_co.pyc
tests/test_es_ni.py
tests/test_es_ni.pyc
tests/test_es_ve.py
tests/test_es_ve.pyc
tests/test_fi.py
tests/test_fi.pyc
tests/test_fr.py
tests/test_fr.pyc
tests/test_fr_be.py
tests/test_fr_be.pyc
tests/test_fr_ch.py
tests/test_fr_ch.pyc
tests/test_fr_dz.py
tests/test_fr_dz.pyc
tests/test_he.py
tests/test_he.pyc
tests/test_id.py
tests/test_id.pyc
tests/test_it.py
tests/test_it.pyc
tests/test_ja.py
tests/test_ja.pyc
tests/test_kn.py
