Metadata-Version: 1.2
Name: numinwords
Version: 0.5.10
Summary: Modules to convert numbers to words. Easily extensible.                Guatemala test
Home-page: https://github.com/sihaysistema/numinwords
Author: Taro Ogawa <tso at users sourceforge net>
Author-email: tos@users.sourceforge.net
Maintainer: m.m@sihaysistema.com SIHAYSISTEMA
Maintainer-email: m.m@sihaysistema.com
License: LGPL
Keywords: number word numbers words convert conversion i18n localisation localization internationalisation internationalization
Platform: UNKNOWN
Classifier: Development Status :: 5 - Production/Stable
Classifier: Intended Audience :: Developers
Classifier: License :: OSI Approved :: GNU Library or Lesser General Public License (LGPL)
Classifier: Programming Language :: Python :: 2.7
Classifier: Programming Language :: Python :: 3
Classifier: Topic :: Software Development :: Internationalization
Classifier: Topic :: Software Development :: Libraries :: Python Modules
Classifier: Topic :: Software Development :: Localization
Classifier: Topic :: Text Processing :: Linguistic
